mesos.cli-0.1.3-py2.7-nspkg.pth
mesos/cli/__init__.py
mesos/cli/cfg.py
mesos/cli/cli.py
mesos/cli/cluster.py
mesos/cli/completion_helpers.py
mesos/cli/exceptions.py
mesos/cli/log.py
mesos/cli/main.py
mesos/cli/master.py
mesos/cli/mesos_file.py
mesos/cli/parser.py
mesos/cli/slave.py
mesos/cli/task.py
mesos/cli/util.py
mesos/cli/zookeeper.py
mesos/cli/cmds/__init__.py
mesos/cli/cmds/cat.py
mesos/cli/cmds/completion.py
mesos/cli/cmds/config.py
mesos/cli/cmds/events.py
mesos/cli/cmds/find.py
mesos/cli/cmds/head.py
mesos/cli/cmds/help.py
mesos/cli/cmds/ls.py
mesos/cli/cmds/ps.py
mesos/cli/cmds/resolve.py
mesos/cli/cmds/scp.py
mesos/cli/cmds/ssh.py
mesos/cli/cmds/state.py
mesos/cli/cmds/tail.py
mesos.cli-0.1.3.data/scripts/mesos-zsh-completion.sh
mesos.cli-0.1.3.dist-info/DESCRIPTION.rst
mesos.cli-0.1.3.dist-info/entry_points.txt
mesos.cli-0.1.3.dist-info/METADATA
mesos.cli-0.1.3.dist-info/metadata.json
mesos.cli-0.1.3.dist-info/namespace_packages.txt
mesos.cli-0.1.3.dist-info/RECORD
mesos.cli-0.1.3.dist-info/top_level.txt
mesos.cli-0.1.3.dist-info/WHEEL
