Metadata-Version: 2.0
Name: mesos.cli
Version: 0.1.3
Summary: Mesos CLI Tools
Home-page: http://pypi.python.org/pypi/mesos.cli
Author: Apache Mesos
Author-email: dev@mesos.apache.org
License: Apache 2.0
Keywords: mesos
Platform: UNKNOWN
Requires-Dist: argcomplete (>=0.8.0)
Requires-Dist: blessings (>=1.5.1)
Requires-Dist: futures (>=2.1.6)
Requires-Dist: importlib (>=1.0.3)
Requires-Dist: kazoo (>=2.0)
Requires-Dist: mesos.interface (>=0.20.0)
Requires-Dist: ordereddict (>=1.1)
Requires-Dist: prettytable (>=0.7.2)
Requires-Dist: protobuf (>=2.5.0,<3)
Requires-Dist: requests (>=2.3.0)
